django_mcp/__init__.py
django_mcp/apps.py
django_mcp/asgi.py
django_mcp/asgi_interceptors.py
django_mcp/asgi_patch_fastmcp.py
django_mcp/context.py
django_mcp/decorators.py
django_mcp/interop_django_fastapi.py
django_mcp/loader.py
django_mcp/log.py
django_mcp/mcp_sdk_patches.py
django_mcp/mcp_sdk_session_replay.py
django_mcp/management/__init__.py
django_mcp/management/commands/__init__.py
django_mcp/management/commands/mcp_inspector.py
django_mcp/tests/__init__.py
django_mcp/tests/test_asgi.py
django_mcp-0.3.1.dist-info/METADATA
django_mcp-0.3.1.dist-info/WHEEL
django_mcp-0.3.1.dist-info/top_level.txt
django_mcp-0.3.1.dist-info/RECORD
